tests/__init__.py
tests/test_golden.py
todoosy/__init__.py
todoosy/formatter.py
todoosy/linter.py
todoosy/parser.py
todoosy/query.py
todoosy/scheme.py
todoosy/sequence.py
todoosy/settings.py
todoosy/types.py
todoosy-0.3.3.dist-info/METADATA
todoosy-0.3.3.dist-info/WHEEL
todoosy-0.3.3.dist-info/top_level.txt
todoosy-0.3.3.dist-info/RECORD
